README.rst
setup.cfg
setup.py
doac/__init__.py
doac/admin.py
doac/compat.py
doac/conf.py
doac/decorators.py
doac/forms.py
doac/http.py
doac/managers.py
doac/middleware.py
doac/models.py
doac/urls.py
doac/utils.py
doac/views.py
doac.egg-info/PKG-INFO
doac.egg-info/SOURCES.txt
doac.egg-info/dependency_links.txt
doac.egg-info/requires.txt
doac.egg-info/top_level.txt
doac/contrib/__init__.py
doac/contrib/rest_framework/__init__.py
doac/contrib/rest_framework/authentication.py
doac/contrib/rest_framework/permissions.py
doac/exceptions/__init__.py
doac/exceptions/access_denied.py
doac/exceptions/base.py
doac/exceptions/insufficient_scope.py
doac/exceptions/invalid_client.py
doac/exceptions/invalid_request.py
doac/exceptions/invalid_scope.py
doac/exceptions/unsupported_grant_type.py
doac/exceptions/unsupported_response_type.py
doac/handlers/__init__.py
doac/handlers/bearer.py