Metadata-Version: 1.1
Name: doac
Version: 0.2.0
Summary: An OAuth2 Consumer application for your Django project.
Home-page: https://github.com/kevin-brown/django-oauth2
Author: Kevin Brown
Author-email: kbrown@rediker.com
License: MIT
Platform: UNKNOWN
Classifier: Development Status :: 3 - Alpha
Classifier: Environment :: Web Environment
Classifier: Framework :: Django
Classifier: Intended Audience :: Developers
Classifier: License :: OSI Approved :: MIT License
Classifier: Programming Language :: Python
Classifier: Programming Language :: Python :: 2.6
Classifier: Programming Language :: Python :: 2.7
